README.md
setup.py
./asyncthread/__init__.py
./asyncthread/thread.py
AsyncThread.egg-info/PKG-INFO
AsyncThread.egg-info/SOURCES.txt
AsyncThread.egg-info/dependency_links.txt
AsyncThread.egg-info/top_level.txt