Metadata-Version: 2.1
Name: AsyncThread
Version: 0.0.1
Summary: A threading implementation for asynchronous functions.
Home-page: https://github.com/Geographs/AsyncThread
Author: Geographs
Author-email: 87452561+Geographs@users.noreply.github.com
License: UNKNOWN
Project-URL: GitHub, https://github.com/Geographs/AsyncThread
Project-URL: Bug Tracker, https://github.com/Geographs/AsyncThread/issues
Platform: UNKNOWN
Classifier: Programming Language :: Python :: 3
Classifier: License :: OSI Approved :: MIT License
Classifier: Operating System :: OS Independent
Requires-Python: >=3.6
